{
    "friends": [
        {
            "name": "Hema",
            "from": "Salem"
        },
        {
            "name": "Dubakkoor",
            "from": "Salem"
        },
        {
            "name": "Minnie",
            "from": "Ettaiyapuram"
        },
        {
            "name": "Donald",
            "from": "Salem"
        }
    ],
    "office": [
        {
            "name": "Bhaiya",
            "from": "Andhra"
        },
        {
            "name": "Guruji",
            "from": "Bihar"
        },
        {
            "name": "Achippu",
            "from": "Telengana"
        },
        {
            "name": "Shinchan",
            "from": "Pondicherry"
        }
    ]
}